qingpi/__init__.py
qingpi/__init__.pyi
qingpi/__main__.py
qingpi/gui/__init__.py
qingpi/gui/__init__.pyi
qingpi/gui/button.py
qingpi/gui/button.pyi
qingpi/gui/gui.py
qingpi/gui/gui.pyi
qingpi/gui/hat.py
qingpi/gui/hat.pyi
qingpi/gui/icon.py
qingpi/gui/icon.pyi
qingpi/gui/slidepad.py
qingpi/gui/slidepad.pyi
qingpi/gui/touchscreen.py
qingpi/gui/touchscreen.pyi
qingpi/gui/util.py
qingpi/gui/util.pyi
qingpi/qingpi.py
qingpi/qingpi.pyi
qingpi_python-0.1.10.dist-info/entry_points.txt
qingpi_python-0.1.10.dist-info/LICENSE
qingpi_python-0.1.10.dist-info/METADATA
qingpi_python-0.1.10.dist-info/WHEEL
qingpi_python-0.1.10.dist-info/RECORD
