Metadata-Version: 2.1
Name: qingpi-python
Version: 0.1.10
Summary: Python library for Qingpi.
Home-page: https://github.com/U-1F992/qingpi
Author: Koutaro Mukai
Author-email: mukai.k1011k@outlook.jp
Requires-Python: >=3.10,<4.0
Classifier: Programming Language :: Python :: 3
Classifier: Programming Language :: Python :: 3.10
Classifier: Programming Language :: Python :: 3.11
Classifier: Programming Language :: Python :: 3.12
Requires-Dist: pyserial (>=3.5,<4.0)
Project-URL: Repository, https://github.com/U-1F992/qingpi
